chattr_auth/__init__.py
chattr_auth/auth0_jwt/__init__.py
chattr_auth/auth0_jwt/jwt_service.py
chattr_auth/base_jwt_service.py
chattr_auth/chattr_jwt/__init__.py
chattr_auth/chattr_jwt/constants.py
chattr_auth/chattr_jwt/helper.py
chattr_auth/chattr_jwt/jwt_service.py
chattr_auth/chattr_jwt/utils.py
chattr_auth/errors.py
chattr_auth/jwt_dataclasses.py
chattr_auth-0.1.0.dist-info/WHEEL
chattr_auth-0.1.0.dist-info/METADATA
chattr_auth-0.1.0.dist-info/RECORD
