Metadata-Version: 2.1
Name: chattr-auth
Version: 0.1.0
Summary: 
Author: Chattr
Author-email: chattra23@gmail.com
Requires-Python: >=3.8
Classifier: Programming Language :: Python :: 3
Classifier: Programming Language :: Python :: 3.10
Classifier: Programming Language :: Python :: 3.8
Classifier: Programming Language :: Python :: 3.9
Requires-Dist: pyjwt[crypto] (>2,<3)
